across/__init__.py
across/__main__.py
across/_channels.py
across/_importer.py
across/_utils.py
across/logging.py
across/servers.py
across-0.1.0.dist-info/LICENSE.txt
across-0.1.0.dist-info/METADATA
across-0.1.0.dist-info/WHEEL
across-0.1.0.dist-info/top_level.txt
across-0.1.0.dist-info/RECORD
